incorporeal_cms-2.0.5.dist-info/licenses/LICENSE.md
incorporealcms/__init__.py
incorporealcms/_version.py
incorporealcms/config.py
incorporealcms/error_pages.py
incorporealcms/feed.py
incorporealcms/markdown.py
incorporealcms/ssg.py
incorporealcms/mdx/__init__.py
incorporealcms/mdx/figures.py
incorporealcms/mdx/pydot.py
incorporealcms/static/css/base.css
incorporealcms/static/css/dark.css
incorporealcms/static/css/light.css
incorporealcms/static/css/plain.css
incorporealcms/static/img/favicon.png
incorporealcms/static/img/favicon.png.license
incorporealcms/static/js/style_switcher.js
incorporealcms/templates/400.html
incorporealcms/templates/404.html
incorporealcms/templates/500.html
incorporealcms/templates/base-wide.html
incorporealcms/templates/base.html
incorporeal_cms-2.0.5.dist-info/METADATA
incorporeal_cms-2.0.5.dist-info/WHEEL
incorporeal_cms-2.0.5.dist-info/entry_points.txt
incorporeal_cms-2.0.5.dist-info/top_level.txt
incorporeal_cms-2.0.5.dist-info/RECORD
