Metadata-Version: 2.4
Name: incorporeal-cms
Version: 2.0.5
Summary: A lightweight static site generator for Markdown-based sites.
Author-email: "Brian S. Stephan" <bss@incorporeal.org>
License: GPL-3.0-or-later
Project-URL: Homepage, https://git.incorporeal.org/bss/incorporeal-cms
Project-URL: Changelog, https://git.incorporeal.org/bss/incorporeal-cms/releases
Project-URL: Bug Tracker, https://git.incorporeal.org/bss/incorporeal-cms/issues
Classifier: Programming Language :: Python :: 3
Classifier: License :: OSI Approved :: GNU General Public License v3 or later (GPLv3+)
Classifier: Operating System :: OS Independent
Classifier: Topic :: Text Processing :: Markup :: Markdown
Requires-Python: >=3.9
License-File: LICENSE.md
Requires-Dist: feedgen
Requires-Dist: jinja2
Requires-Dist: Markdown
Requires-Dist: termcolor
Provides-Extra: dev
Requires-Dist: bandit; extra == "dev"
Requires-Dist: dlint; extra == "dev"
Requires-Dist: flake8; extra == "dev"
Requires-Dist: flake8-blind-except; extra == "dev"
Requires-Dist: flake8-builtins; extra == "dev"
Requires-Dist: flake8-docstrings; extra == "dev"
Requires-Dist: flake8-executable; extra == "dev"
Requires-Dist: flake8-fixme; extra == "dev"
Requires-Dist: flake8-isort; extra == "dev"
Requires-Dist: flake8-logging-format; extra == "dev"
Requires-Dist: flake8-mutable; extra == "dev"
Requires-Dist: flake8-pyproject; extra == "dev"
Requires-Dist: mypy; extra == "dev"
Requires-Dist: pip-tools; extra == "dev"
Requires-Dist: pydot; extra == "dev"
Requires-Dist: pytest; extra == "dev"
Requires-Dist: pytest-cov; extra == "dev"
Requires-Dist: reuse; extra == "dev"
Requires-Dist: safety; extra == "dev"
Requires-Dist: setuptools-scm; extra == "dev"
Requires-Dist: tox; extra == "dev"
Requires-Dist: twine; extra == "dev"
Provides-Extra: dot
Requires-Dist: pydot; extra == "dot"
Dynamic: license-file
